mate_query/__init__.py
mate_query/cfl.py
mate_query/config.py
mate_query/db.py
mate_query/storage.py
mate_query/string.py
mate_query/cpg/__init__.py
mate_query/cpg/models/__init__.py
mate_query/cpg/models/_typechecking.py
mate_query/cpg/models/docs.py
mate_query/cpg/models/core/__init__.py
mate_query/cpg/models/core/base.py
mate_query/cpg/models/core/cpg.py
mate_query/cpg/models/core/edge.py
mate_query/cpg/models/core/node.py
mate_query/cpg/models/core/relationships.py
mate_query/cpg/models/node/__init__.py
mate_query/cpg/models/node/_typechecking.py
mate_query/cpg/models/node/analysis.py
mate_query/cpg/models/node/dwarf.py
mate_query/cpg/models/node/translation_unit.py
mate_query/cpg/models/node/ast/__init__.py
mate_query/cpg/models/node/ast/bin.py
mate_query/cpg/models/node/ast/llvm.py
mate_query/cpg/models/node/ast/mc.py
mate_query/cpg/query/__init__.py
mate_query/cpg/query/cfg_avoiding.py
mate_query/cpg/query/control_flow.py
mate_query/cpg/query/dataflow.py
mate_query/cpg/query/known_function_whitelist.py
mate_query/cpg/query/query_helpers.py
mate_query-0.0.1.dist-info/METADATA
mate_query-0.0.1.dist-info/WHEEL
mate_query-0.0.1.dist-info/top_level.txt
mate_query-0.0.1.dist-info/RECORD
