Metadata-Version: 2.1
Name: mate-query
Version: 0.0.1
Summary: The MATE CPG query language and DB models
Author: The MATE authors
Author-email: mate@galois.com
License: BSD-3-Clause
Project-URL: Documentation, https://mate.galois.com
Platform: any
Requires-Python: >=3.8
Requires-Dist: sqlalchemy (==1.3.12)
Requires-Dist: psycopg2-binary (==2.8.5)
